zazo/__init__.py
zazo/abc.py
zazo/api.py
zazo/exceptions.py
zazo/resolver.py
zazo-0.0.0a3.dist-info/LICENSE
zazo-0.0.0a3.dist-info/WHEEL
zazo-0.0.0a3.dist-info/METADATA
zazo-0.0.0a3.dist-info/RECORD
