Metadata-Version: 2.1
Name: zazo
Version: 0.0.0a3
Summary: An Extensible Dependency Resolver written in Python
Home-page: https://github.com/pradyunsg/zazo
License: UNKNOWN
Author: Pradyun Gedam
Author-email: pradyunsg@gmail.com
Classifier: License :: OSI Approved :: MIT License
Classifier: Intended Audience :: Developers
Classifier: Programming Language :: Python :: 2
Classifier: Programming Language :: Python :: 2.7
Classifier: Programming Language :: Python :: 3
Classifier: Programming Language :: Python :: 3.4
Classifier: Programming Language :: Python :: 3.5
Classifier: Programming Language :: Python :: 3.6
Classifier: Programming Language :: Python :: Implementation :: PyPy
Requires-Dist: packaging
Requires-Dist: six
Project-URL: Documentation, https://zazo.readthedocs.io/en/latest/
